Metadata-Version: 2.1
Name: datalad-crawler
Version: 1.0.2
Summary: DataLad extension package for crawling external web resources into an automated data distribution
Author: The DataLad Team and Contributors
Author-email: team@datalad.org
License-File: COPYING
Requires-Dist: datalad (>=0.14.0)
Requires-Dist: scrapy (>=1.1.0)
Provides-Extra: core
Requires-Dist: datalad (>=0.14.0) ; extra == 'core'
Requires-Dist: scrapy (>=1.1.0) ; extra == 'core'
Provides-Extra: devel
Requires-Dist: datalad (>=0.14.0) ; extra == 'devel'
Requires-Dist: scrapy (>=1.1.0) ; extra == 'devel'
Requires-Dist: sphinx ; extra == 'devel'
Requires-Dist: sphinx-rtd-theme ; extra == 'devel'
Requires-Dist: datalad (>=0.17.0) ; extra == 'devel'
Requires-Dist: datalad-deprecated (>=0.2.6) ; extra == 'devel'
Requires-Dist: pytest (>=7.0) ; extra == 'devel'
Requires-Dist: pytest-cov ; extra == 'devel'
Requires-Dist: mock ; extra == 'devel'
Provides-Extra: devel-docs
Requires-Dist: sphinx ; extra == 'devel-docs'
Requires-Dist: sphinx-rtd-theme ; extra == 'devel-docs'
Provides-Extra: tests
Requires-Dist: datalad (>=0.17.0) ; extra == 'tests'
Requires-Dist: datalad-deprecated (>=0.2.6) ; extra == 'tests'
Requires-Dist: pytest (>=7.0) ; extra == 'tests'
Requires-Dist: pytest-cov ; extra == 'tests'
Requires-Dist: mock ; extra == 'tests'
